tzBJC/__init__.py
tzBJC/cli.py
tzBJC/core.py
tzBJC/gui.py
tzbjc-0.2.17.dist-info/licenses/LICENSE
tzbjc-0.2.17.dist-info/METADATA
tzbjc-0.2.17.dist-info/WHEEL
tzbjc-0.2.17.dist-info/entry_points.txt
tzbjc-0.2.17.dist-info/top_level.txt
tzbjc-0.2.17.dist-info/RECORD
