Metadata-Version: 2.4
Name: tzBJC
Version: 0.2.17
Summary: Convert binary files to signed JSON and back, with zstd compression.
Author-email: Matthew Craig <taggedzi.mpc@gmail.com>
License-Expression: MIT
Project-URL: Homepage, https://github.com/taggedzi/tzBJC
Keywords: json,binary,converter,zstandard,cli,gui,library,compression
Classifier: Programming Language :: Python :: 3
Classifier: Operating System :: OS Independent
Classifier: Development Status :: 4 - Beta
Classifier: Environment :: Console
Classifier: Environment :: X11 Applications :: Qt
Classifier: Topic :: Utilities
Requires-Python: >=3.8
License-File: LICENSE
Requires-Dist: PySide6==6.9.0
Requires-Dist: PySide6_Addons==6.9.0
Requires-Dist: PySide6_Essentials==6.9.0
Requires-Dist: zstandard==0.23.0
Provides-Extra: dev
Requires-Dist: coverage==7.8.0; extra == "dev"
Requires-Dist: invoke==2.2.0; extra == "dev"
Requires-Dist: pdoc==15.0.3; extra == "dev"
Requires-Dist: pytest==8.3.5; extra == "dev"
Requires-Dist: pytest-cov==6.1.1; extra == "dev"
Requires-Dist: pytest-qt==4.4.0; extra == "dev"
Requires-Dist: toml==0.10.2; extra == "dev"
Dynamic: license-file
